{
  "annotations": {
    "list": [
      {
        "builtIn": 1,
        "datasource": {"type": "grafana", "uid": "-- Grafana --"},
        "enable": true,
        "hide": true,
        "iconColor": "rgba(0, 211, 255, 1)",
        "name": "Annotations & Alerts",
        "type": "dashboard"
      }
    ]
  },
  "editable": true,
  "fiscalYearStartMonth": 0,
  "graphTooltip": 1,
  "id": null,
  "links": [],
  "liveNow": false,
  "panels": [
    {
      "collapsed": false,
      "gridPos": {"h": 1, "w": 24, "x": 0, "y": 0},
      "id": 1,
      "panels": [],
      "title": "🗄️ Connection Pool (PostgreSQL)",
      "type": "row"
    },
    {
      "datasource": {"type": "prometheus", "uid": "prometheus"},
      "description": "Número atual de conexões abertas no pool",
      "fieldConfig": {
        "defaults": {
          "color": {"mode": "thresholds"},
          "mappings": [],
          "thresholds": {
            "mode": "absolute",
            "steps": [
              {"color": "green", "value": null},
              {"color": "yellow", "value": 20},
              {"color": "red", "value": 24}
            ]
          },
          "unit": "short"
        }
      },
      "gridPos": {"h": 6, "w": 4, "x": 0, "y": 1},
      "id": 2,
      "options": {
        "colorMode": "value",
        "graphMode": "area",
        "justifyMode": "auto",
        "orientation": "auto",
        "reduceOptions": {"calcs": ["lastNotNull"], "fields": "", "values": false},
        "textMode": "auto"
      },
      "pluginVersion": "10.0.0",
      "targets": [
        {
          "datasource": {"type": "prometheus", "uid": "prometheus"},
          "expr": "db_sql_connection_open",
          "refId": "A"
        }
      ],
      "title": "Conexões Abertas",
      "type": "stat"
    },
    {
      "datasource": {"type": "prometheus", "uid": "prometheus"},
      "description": "Máximo de conexões permitidas no pool",
      "fieldConfig": {
        "defaults": {
          "color": {"mode": "thresholds"},
          "mappings": [],
          "thresholds": {
            "mode": "absolute",
            "steps": [
              {"color": "blue", "value": null}
            ]
          },
          "unit": "short"
        }
      },
      "gridPos": {"h": 6, "w": 4, "x": 4, "y": 1},
      "id": 3,
      "options": {
        "colorMode": "value",
        "graphMode": "none",
        "justifyMode": "auto",
        "orientation": "auto",
        "reduceOptions": {"calcs": ["lastNotNull"], "fields": "", "values": false},
        "textMode": "auto"
      },
      "pluginVersion": "10.0.0",
      "targets": [
        {
          "datasource": {"type": "prometheus", "uid": "prometheus"},
          "expr": "db_sql_connection_max_open",
          "refId": "A"
        }
      ],
      "title": "Pool Máximo",
      "type": "stat"
    },
    {
      "datasource": {"type": "prometheus", "uid": "prometheus"},
      "description": "Utilização do pool (%)",
      "fieldConfig": {
        "defaults": {
          "color": {"mode": "thresholds"},
          "mappings": [],
          "max": 100,
          "min": 0,
          "thresholds": {
            "mode": "absolute",
            "steps": [
              {"color": "green", "value": null},
              {"color": "yellow", "value": 70},
              {"color": "red", "value": 90}
            ]
          },
          "unit": "percent"
        }
      },
      "gridPos": {"h": 6, "w": 4, "x": 8, "y": 1},
      "id": 4,
      "options": {
        "orientation": "auto",
        "reduceOptions": {"calcs": ["lastNotNull"], "fields": "", "values": false},
        "showThresholdLabels": false,
        "showThresholdMarkers": true
      },
      "pluginVersion": "10.0.0",
      "targets": [
        {
          "datasource": {"type": "prometheus", "uid": "prometheus"},
          "expr": "(db_sql_connection_open / db_sql_connection_max_open) * 100",
          "refId": "A"
        }
      ],
      "title": "Pool Utilization",
      "type": "gauge"
    },
    {
      "datasource": {"type": "prometheus", "uid": "prometheus"},
      "description": "Total de waits por segundo",
      "fieldConfig": {
        "defaults": {
          "color": {"mode": "thresholds"},
          "mappings": [],
          "thresholds": {
            "mode": "absolute",
            "steps": [
              {"color": "green", "value": null},
              {"color": "yellow", "value": 10},
              {"color": "red", "value": 50}
            ]
          },
          "unit": "ops"
        }
      },
      "gridPos": {"h": 6, "w": 4, "x": 12, "y": 1},
      "id": 5,
      "options": {
        "colorMode": "value",
        "graphMode": "area",
        "justifyMode": "auto",
        "orientation": "auto",
        "reduceOptions": {"calcs": ["lastNotNull"], "fields": "", "values": false},
        "textMode": "auto"
      },
      "pluginVersion": "10.0.0",
      "targets": [
        {
          "datasource": {"type": "prometheus", "uid": "prometheus"},
          "expr": "rate(db_sql_connection_wait_total[1m])",
          "refId": "A"
        }
      ],
      "title": "Connection Waits/sec",
      "type": "stat"
    },
    {
      "datasource": {"type": "prometheus", "uid": "prometheus"},
      "description": "Evolução das conexões abertas vs máximo",
      "fieldConfig": {
        "defaults": {
          "color": {"mode": "palette-classic"},
          "custom": {
            "axisCenteredZero": false,
            "axisColorMode": "text",
            "axisLabel": "",
            "axisPlacement": "auto",
            "barAlignment": 0,
            "drawStyle": "line",
            "fillOpacity": 10,
            "gradientMode": "none",
            "hideFrom": {"tooltip": false, "viz": false, "legend": false},
            "lineInterpolation": "linear",
            "lineWidth": 2,
            "pointSize": 5,
            "scaleDistribution": {"type": "linear"},
            "showPoints": "never",
            "spanNulls": false,
            "stacking": {"group": "A", "mode": "none"},
            "thresholdsStyle": {"mode": "off"}
          },
          "mappings": [],
          "thresholds": {"mode": "absolute", "steps": [{"color": "green", "value": null}]},
          "unit": "short"
        }
      },
      "gridPos": {"h": 8, "w": 12, "x": 0, "y": 7},
      "id": 6,
      "options": {
        "legend": {"calcs": [], "displayMode": "list", "placement": "bottom", "showLegend": true},
        "tooltip": {"mode": "multi", "sort": "none"}
      },
      "pluginVersion": "10.0.0",
      "targets": [
        {
          "datasource": {"type": "prometheus", "uid": "prometheus"},
          "expr": "db_sql_connection_open",
          "legendFormat": "Open",
          "refId": "A"
        },
        {
          "datasource": {"type": "prometheus", "uid": "prometheus"},
          "expr": "db_sql_connection_max_open",
          "legendFormat": "Max",
          "refId": "B"
        }
      ],
      "title": "Connection Pool Over Time",
      "type": "timeseries"
    },
    {
      "datasource": {"type": "prometheus", "uid": "prometheus"},
      "description": "Taxa de conexões fechadas por motivo",
      "fieldConfig": {
        "defaults": {
          "color": {"mode": "palette-classic"},
          "custom": {
            "axisCenteredZero": false,
            "axisColorMode": "text",
            "axisLabel": "connections/sec",
            "axisPlacement": "auto",
            "barAlignment": 0,
            "drawStyle": "line",
            "fillOpacity": 10,
            "gradientMode": "none",
            "hideFrom": {"tooltip": false, "viz": false, "legend": false},
            "lineInterpolation": "linear",
            "lineWidth": 2,
            "pointSize": 5,
            "scaleDistribution": {"type": "linear"},
            "showPoints": "never",
            "spanNulls": false,
            "stacking": {"group": "A", "mode": "normal"},
            "thresholdsStyle": {"mode": "off"}
          },
          "mappings": [],
          "thresholds": {"mode": "absolute", "steps": [{"color": "green", "value": null}]},
          "unit": "ops"
        }
      },
      "gridPos": {"h": 8, "w": 12, "x": 12, "y": 7},
      "id": 7,
      "options": {
        "legend": {"calcs": [], "displayMode": "list", "placement": "bottom", "showLegend": true},
        "tooltip": {"mode": "multi", "sort": "none"}
      },
      "pluginVersion": "10.0.0",
      "targets": [
        {
          "datasource": {"type": "prometheus", "uid": "prometheus"},
          "expr": "rate(db_sql_connection_closed_max_idle_total[5m])",
          "legendFormat": "Max Idle",
          "refId": "A"
        },
        {
          "datasource": {"type": "prometheus", "uid": "prometheus"},
          "expr": "rate(db_sql_connection_closed_max_lifetime_total[5m])",
          "legendFormat": "Max Lifetime",
          "refId": "B"
        },
        {
          "datasource": {"type": "prometheus", "uid": "prometheus"},
          "expr": "rate(db_sql_connection_closed_max_idle_time_total[5m])",
          "legendFormat": "Max Idle Time",
          "refId": "C"
        }
      ],
      "title": "Connection Closures by Reason",
      "type": "timeseries"
    },
    {
      "collapsed": false,
      "gridPos": {"h": 1, "w": 24, "x": 0, "y": 15},
      "id": 8,
      "panels": [],
      "title": "⚡ Query Performance",
      "type": "row"
    },
    {
      "datasource": {"type": "prometheus", "uid": "prometheus"},
      "description": "Latência P95 de queries SQL (ms)",
      "fieldConfig": {
        "defaults": {
          "color": {"mode": "thresholds"},
          "mappings": [],
          "thresholds": {
            "mode": "absolute",
            "steps": [
              {"color": "green", "value": null},
              {"color": "yellow", "value": 100},
              {"color": "red", "value": 200}
            ]
          },
          "unit": "ms"
        }
      },
      "gridPos": {"h": 6, "w": 6, "x": 0, "y": 16},
      "id": 9,
      "options": {
        "colorMode": "value",
        "graphMode": "area",
        "justifyMode": "auto",
        "orientation": "auto",
        "reduceOptions": {"calcs": ["lastNotNull"], "fields": "", "values": false},
        "textMode": "auto"
      },
      "pluginVersion": "10.0.0",
      "targets": [
        {
          "datasource": {"type": "prometheus", "uid": "prometheus"},
          "expr": "histogram_quantile(0.95, rate(db_sql_latency_milliseconds_bucket[5m]))",
          "refId": "A"
        }
      ],
      "title": "Query Latency P95",
      "type": "stat"
    },
    {
      "datasource": {"type": "prometheus", "uid": "prometheus"},
      "description": "Total de queries por segundo",
      "fieldConfig": {
        "defaults": {
          "color": {"mode": "thresholds"},
          "mappings": [],
          "thresholds": {
            "mode": "absolute",
            "steps": [
              {"color": "green", "value": null}
            ]
          },
          "unit": "reqps"
        }
      },
      "gridPos": {"h": 6, "w": 6, "x": 6, "y": 16},
      "id": 10,
      "options": {
        "colorMode": "value",
        "graphMode": "area",
        "justifyMode": "auto",
        "orientation": "auto",
        "reduceOptions": {"calcs": ["lastNotNull"], "fields": "", "values": false},
        "textMode": "auto"
      },
      "pluginVersion": "10.0.0",
      "targets": [
        {
          "datasource": {"type": "prometheus", "uid": "prometheus"},
          "expr": "rate(db_sql_latency_milliseconds_count[1m])",
          "refId": "A"
        }
      ],
      "title": "Queries/sec",
      "type": "stat"
    },
    {
      "datasource": {"type": "prometheus", "uid": "prometheus"},
      "description": "Latência de queries (P50/P95/P99)",
      "fieldConfig": {
        "defaults": {
          "color": {"mode": "palette-classic"},
          "custom": {
            "axisCenteredZero": false,
            "axisColorMode": "text",
            "axisLabel": "milliseconds",
            "axisPlacement": "auto",
            "barAlignment": 0,
            "drawStyle": "line",
            "fillOpacity": 10,
            "gradientMode": "none",
            "hideFrom": {"tooltip": false, "viz": false, "legend": false},
            "lineInterpolation": "linear",
            "lineWidth": 2,
            "pointSize": 5,
            "scaleDistribution": {"type": "linear"},
            "showPoints": "never",
            "spanNulls": false,
            "stacking": {"group": "A", "mode": "none"},
            "thresholdsStyle": {"mode": "off"}
          },
          "mappings": [],
          "thresholds": {"mode": "absolute", "steps": [{"color": "green", "value": null}]},
          "unit": "ms"
        }
      },
      "gridPos": {"h": 8, "w": 12, "x": 0, "y": 22},
      "id": 11,
      "options": {
        "legend": {"calcs": [], "displayMode": "list", "placement": "bottom", "showLegend": true},
        "tooltip": {"mode": "multi", "sort": "none"}
      },
      "pluginVersion": "10.0.0",
      "targets": [
        {
          "datasource": {"type": "prometheus", "uid": "prometheus"},
          "expr": "histogram_quantile(0.50, rate(db_sql_latency_milliseconds_bucket[5m]))",
          "legendFormat": "P50",
          "refId": "A"
        },
        {
          "datasource": {"type": "prometheus", "uid": "prometheus"},
          "expr": "histogram_quantile(0.95, rate(db_sql_latency_milliseconds_bucket[5m]))",
          "legendFormat": "P95",
          "refId": "B"
        },
        {
          "datasource": {"type": "prometheus", "uid": "prometheus"},
          "expr": "histogram_quantile(0.99, rate(db_sql_latency_milliseconds_bucket[5m]))",
          "legendFormat": "P99",
          "refId": "C"
        }
      ],
      "title": "Query Latency (P50/P95/P99)",
      "type": "timeseries"
    },
    {
      "datasource": {"type": "prometheus", "uid": "prometheus"},
      "description": "Taxa de queries por segundo ao longo do tempo",
      "fieldConfig": {
        "defaults": {
          "color": {"mode": "palette-classic"},
          "custom": {
            "axisCenteredZero": false,
            "axisColorMode": "text",
            "axisLabel": "queries/sec",
            "axisPlacement": "auto",
            "barAlignment": 0,
            "drawStyle": "line",
            "fillOpacity": 10,
            "gradientMode": "none",
            "hideFrom": {"tooltip": false, "viz": false, "legend": false},
            "lineInterpolation": "linear",
            "lineWidth": 2,
            "pointSize": 5,
            "scaleDistribution": {"type": "linear"},
            "showPoints": "never",
            "spanNulls": false,
            "stacking": {"group": "A", "mode": "none"},
            "thresholdsStyle": {"mode": "off"}
          },
          "mappings": [],
          "thresholds": {"mode": "absolute", "steps": [{"color": "green", "value": null}]},
          "unit": "reqps"
        }
      },
      "gridPos": {"h": 8, "w": 12, "x": 12, "y": 22},
      "id": 12,
      "options": {
        "legend": {"calcs": [], "displayMode": "list", "placement": "bottom", "showLegend": true},
        "tooltip": {"mode": "multi", "sort": "none"}
      },
      "pluginVersion": "10.0.0",
      "targets": [
        {
          "datasource": {"type": "prometheus", "uid": "prometheus"},
          "expr": "rate(db_sql_latency_milliseconds_count[1m])",
          "legendFormat": "Queries/sec",
          "refId": "A"
        }
      ],
      "title": "Query Rate Over Time",
      "type": "timeseries"
    }
  ],
  "refresh": "5s",
  "schemaVersion": 38,
  "style": "dark",
  "tags": ["financial", "database", "postgresql", "real-metrics"],
  "templating": {"list": []},
  "time": {"from": "now-15m", "to": "now"},
  "timepicker": {},
  "timezone": "browser",
  "title": "Financial - Database (Real Metrics)",
  "uid": "financial-db-real",
  "version": 1,
  "weekStart": ""
}
